samwich_cli/controller.py
samwich_cli/file_utils.py
samwich_cli/main.py
samwich_cli/model.py
samwich_cli/sam_utils.py
samwich_cli-0.18.0.dist-info/METADATA
samwich_cli-0.18.0.dist-info/WHEEL
samwich_cli-0.18.0.dist-info/entry_points.txt
samwich_cli-0.18.0.dist-info/licenses/LICENSE
samwich_cli-0.18.0.dist-info/RECORD
