Metadata-Version: 2.4
Name: samwich-cli
Version: 0.18.0
Summary: A CLI tool to streamline AWS SAM deployments for Python Lambda functions by managing dependencies, executing sam build, and maintaining consistent folder structures.
Project-URL: repository, https://github.com/agnostella/samwich-cli
License-Expression: MIT
License-File: LICENSE
Keywords: AWS,CLI,SAM
Classifier: Development Status :: 4 - Beta
Classifier: Environment :: Console
Classifier: Intended Audience :: Developers
Classifier: Intended Audience :: Information Technology
Classifier: Operating System :: OS Independent
Classifier: Programming Language :: Python :: 3
Classifier: Programming Language :: Python :: 3.9
Classifier: Programming Language :: Python :: 3.10
Classifier: Programming Language :: Python :: 3.11
Classifier: Programming Language :: Python :: 3.12
Classifier: Programming Language :: Python :: 3.13
Classifier: Topic :: Software Development :: Build Tools
Classifier: Topic :: Utilities
Requires-Python: >=3.9
Requires-Dist: aws-sam-cli<=2.0.0,>=1.136.0
Requires-Dist: click~=8.1.8
